cvasl/.RData
cvasl/CVASL_RELIEF.R
cvasl/CVASL_RELIEF_DRIVER.R
cvasl/__init__.py
cvasl/__main__.py
cvasl/_version.py
cvasl/combatPP.R
cvasl/dataset.py
cvasl/harmonizer_cli.py
cvasl/harmonizers.py
cvasl/harmony.py.old.py
cvasl/params.yaml
cvasl/prediction.py
cvasl/seperated.py.old
cvasl/utils.R
cvasl/deepresearch/.pylintrc
cvasl/deepresearch/__init__.py
cvasl/deepresearch/data.py
cvasl/deepresearch/job.sh
cvasl/deepresearch/jobxai.sh
cvasl/deepresearch/test_stats.py
cvasl/deepresearch/train.py
cvasl/deepresearch/utils.py
cvasl/deepresearch/xai.py
cvasl/deepresearch/Harvard-Oxford_cortical_and_subcortical_structural_atlases/HarvardOxford-cort-maxprob-thr0-1mm.nii.gz
cvasl/deepresearch/Harvard-Oxford_cortical_and_subcortical_structural_atlases/HarvardOxford-cort-maxprob-thr0-2mm.nii.gz
cvasl/deepresearch/Harvard-Oxford_cortical_and_subcortical_structural_atlases/HarvardOxford-cort-maxprob-thr25-1mm.nii.gz
cvasl/deepresearch/Harvard-Oxford_cortical_and_subcortical_structural_atlases/HarvardOxford-cort-maxprob-thr25-2mm.nii.gz
cvasl/deepresearch/Harvard-Oxford_cortical_and_subcortical_structural_atlases/HarvardOxford-cort-maxprob-thr50-1mm.nii.gz
cvasl/deepresearch/Harvard-Oxford_cortical_and_subcortical_structural_atlases/HarvardOxford-cort-maxprob-thr50-2mm.nii.gz
cvasl/deepresearch/Harvard-Oxford_cortical_and_subcortical_structural_atlases/HarvardOxford-cort_and_sub-maxprob-thr25-1mm.nii.gz.nii.gz
cvasl/deepresearch/Harvard-Oxford_cortical_and_subcortical_structural_atlases/HarvardOxford-cort_and_sub-maxprob-thr25-1mm.nii.gz_1.nii.gz
cvasl/deepresearch/Harvard-Oxford_cortical_and_subcortical_structural_atlases/HarvardOxford-sub-maxprob-thr0-1mm.nii.gz
cvasl/deepresearch/Harvard-Oxford_cortical_and_subcortical_structural_atlases/HarvardOxford-sub-maxprob-thr0-2mm.nii.gz
cvasl/deepresearch/Harvard-Oxford_cortical_and_subcortical_structural_atlases/HarvardOxford-sub-maxprob-thr25-1mm.nii.gz
cvasl-0.2.3.dist-info/licenses/LICENSE
cvasl-0.2.3.dist-info/licenses/NOTICE.md
cvasl-0.2.3.dist-info/METADATA
cvasl-0.2.3.dist-info/WHEEL
cvasl-0.2.3.dist-info/top_level.txt
cvasl-0.2.3.dist-info/RECORD
