Metadata-Version: 2.4
Name: cvasl
Version: 0.2.3
Summary: A package for analysis of MRI
Author-email: A team including the NLeSC and the Amsterdam Medical Center <s.amiri@esciencecenter.nl>
Maintainer-email: Saba Amiri <s.amiri@esciencecenter.nl>, Peter Kok <p.kok@esciencecenter.nl>, Mathijs Dijsselhof <m.b.dijsselhof@amsterdamumc.nl>
License:                                  Apache License
Project-URL: Repository, https://github.com/brainspinner/cvasl
Keywords: MRI,harmonisation
Classifier: Development Status :: 2 - Pre-Alpha
Classifier: Intended Audience :: Science/Research
Classifier: Topic :: Scientific/Engineering
Classifier: License :: OSI Approved :: Apache Software License
Classifier: Programming Language :: Python :: 3
Classifier: Programming Language :: Python :: 3.10
Classifier: Programming Language :: Python :: 3.11
Classifier: Programming Language :: Python :: 3.12
Requires-Python: >=3.10
License-File: LICENSE
License-File: NOTICE.md
Requires-Dist: k_means_constrained>=0.5.2
Requires-Dist: kneed
Requires-Dist: matplotlib
Requires-Dist: neuroharmonize>=2.4.5
Requires-Dist: neurocombat>=0.2.12
Requires-Dist: nibabel
Requires-Dist: nipy
Requires-Dist: numpy<2
Requires-Dist: opencv-python
Requires-Dist: pandas<3,>=1.2.0
Requires-Dist: patsy
Requires-Dist: pingouin
Requires-Dist: grad-cam
Requires-Dist: pyxdf
Requires-Dist: scikit-image
Requires-Dist: scikit-learn>=0.23.2
Requires-Dist: scipy>=1.5.4
Requires-Dist: seaborn
Requires-Dist: simpleitk>=2.0.1
Requires-Dist: statsmodels>=0.14.4
Requires-Dist: torch
Requires-Dist: torchvision
Requires-Dist: tqdm>=4.59
Requires-Dist: umap-learn>=0.5.1
Requires-Dist: wandb
Requires-Dist: yellowbrick>=1.3
Provides-Extra: dev
Requires-Dist: ipympl; extra == "dev"
Requires-Dist: isort; extra == "dev"
Requires-Dist: nbmake; extra == "dev"
Requires-Dist: pycodestyle; extra == "dev"
Requires-Dist: pytest; extra == "dev"
Requires-Dist: pytest-datadir>=1.7.2; extra == "dev"
Requires-Dist: build; extra == "dev"
Provides-Extra: docs
Requires-Dist: sphinx; extra == "docs"
Requires-Dist: piccolo_theme; extra == "docs"
Dynamic: license-file
